[
    {
        "title": "Graphic Designer & Content Creator (International Work) – URGENT HIRING",
        "link": "https://jobs.bdjobs.com/jobdetails/?id=1436711&fcatId=8&ln=1",
        "deadline": "Deadline:15 Dec2025"
    },
    {
        "title": "Senior Engineer (Surveillance - CCTV & Network)",
        "link": "https://jobs.bdjobs.com/jobdetails/?id=1436447&fcatId=8&ln=1",
        "deadline": "Deadline:31 Dec2025"
    },
    {
        "title": "Software Developer (PHP Developer (CodeIgniter/Laravel)",
        "link": "https://jobs.bdjobs.com/jobdetails/?id=1436556&fcatId=8&ln=1",
        "deadline": "Deadline:3 Jan2026"
    },
    {
        "title": "Employment Support Officer",
        "link": "https://jobs.bdjobs.com/jobdetails/?id=1436298&fcatId=8&ln=1",
        "deadline": "Deadline:13 Dec2025"
    },
    {
        "title": "IT Support with Digital Marketing Specialist",
        "link": "https://jobs.bdjobs.com/jobdetails/?id=1436550&fcatId=8&ln=1",
        "deadline": "Deadline:14 Dec2025"
    },
    {
        "title": "ISP Support Engineer - NOC",
        "link": "https://jobs.bdjobs.com/jobdetails/?id=1436411&fcatId=8&ln=1",
        "deadline": "Deadline:11 Dec2025"
    },
    {
        "title": "Junior Executive (Web Development)",
        "link": "https://jobs.bdjobs.com/jobdetails/?id=1436444&fcatId=8&ln=1",
        "deadline": "Deadline:14 Dec2025"
    },
    {
        "title": "Software Developer (Full Stack)",
        "link": "https://jobs.bdjobs.com/jobdetails/?id=1435836&fcatId=8&ln=1",
        "deadline": "Deadline:20 Dec2025"
    },
    {
        "title": "Deputy Manager - Corporate Customer support",
        "link": "https://jobs.bdjobs.com/jobdetails/?id=1436311&fcatId=8&ln=1",
        "deadline": "Deadline:31 Dec2025"
    },
    {
        "title": "Network Engineer",
        "link": "https://jobs.bdjobs.com/jobdetails/?id=1436225&fcatId=8&ln=1",
        "deadline": "Deadline:2 Jan2026"
    },
    {
        "title": "Junior Laravel Developer",
        "link": "https://jobs.bdjobs.com/jobdetails/?id=1436272&fcatId=8&ln=1",
        "deadline": "Deadline:14 Dec2025"
    },
    {
        "title": "Assistant Manager (Sales & Marketing)",
        "link": "https://jobs.bdjobs.com/jobdetails/?id=1436177&fcatId=8&ln=1",
        "deadline": "Deadline:2 Jan2026"
    },
    {
        "title": "Executive / Sr. Executive (Sales & Marketing)",
        "link": "https://jobs.bdjobs.com/jobdetails/?id=1436179&fcatId=8&ln=1",
        "deadline": "Deadline:2 Jan2026"
    },
    {
        "title": "Internship - Odoo Software Management",
        "link": "https://jobs.bdjobs.com/jobdetails/?id=1436184&fcatId=8&ln=1",
        "deadline": "Deadline:16 Dec2025"
    },
    {
        "title": "Web Developer",
        "link": "https://jobs.bdjobs.com/jobdetails/?id=1436127&fcatId=8&ln=1",
        "deadline": "Deadline:10 Dec2025"
    },
    {
        "title": "SAP ABAP Developer",
        "link": "https://jobs.bdjobs.com/jobdetails/?id=1436052&fcatId=8&ln=1",
        "deadline": "Deadline:31 Dec2025"
    },
    {
        "title": "Help Desk Executive",
        "link": "https://jobs.bdjobs.com/jobdetails/?id=1435996&fcatId=8&ln=1",
        "deadline": "Deadline:20 Dec2025"
    },
    {
        "title": "System Admin (Servers, Storage, Network)",
        "link": "https://jobs.bdjobs.com/jobdetails/?id=1435976&fcatId=8&ln=1",
        "deadline": "Deadline:22 Dec2025"
    },
    {
        "title": "Sr. Database Administrator",
        "link": "https://jobs.bdjobs.com/jobdetails/?id=1435952&fcatId=8&ln=1",
        "deadline": "Deadline:25 Dec2025"
    },
    {
        "title": "Digital Marketing Executive",
        "link": "https://jobs.bdjobs.com/jobdetails/?id=1435945&fcatId=8&ln=1",
        "deadline": "Deadline:2 Jan2026"
    },
    {
        "title": "Sr. Web Programmer/ Sr. Software Engineer",
        "link": "https://jobs.bdjobs.com/jobdetails/?id=1435921&fcatId=8&ln=1",
        "deadline": "Deadline:25 Dec2025"
    },
    {
        "title": "NOC Assistant Engineer",
        "link": "https://jobs.bdjobs.com/jobdetails/?id=1435859&fcatId=8&ln=1",
        "deadline": "Deadline:16 Dec2025"
    },
    {
        "title": "Content Creator",
        "link": "https://jobs.bdjobs.com/jobdetails/?id=1434252&fcatId=8&ln=1",
        "deadline": "Deadline:1 Jan2026"
    },
    {
        "title": "Assistant Manager - Enterprise System Administration",
        "link": "https://jobs.bdjobs.com/jobdetails/?id=1435669&fcatId=8&ln=1",
        "deadline": "Deadline:13 Dec2025"
    },
    {
        "title": "Customer Home Support",
        "link": "https://jobs.bdjobs.com/jobdetails/?id=1435738&fcatId=8&ln=1",
        "deadline": "Deadline:31 Dec2025"
    },
    {
        "title": "FullStack Wordpress Developer",
        "link": "https://jobs.bdjobs.com/jobdetails/?id=1435729&fcatId=8&ln=1",
        "deadline": "Deadline:7 Dec2025"
    },
    {
        "title": "IT Project Coordinator",
        "link": "https://jobs.bdjobs.com/jobdetails/?id=1435057&fcatId=8&ln=1",
        "deadline": "Deadline:15 Dec2025"
    },
    {
        "title": "MIS Executive",
        "link": "https://jobs.bdjobs.com/jobdetails/?id=1435448&fcatId=8&ln=1",
        "deadline": "Deadline:15 Dec2025"
    },
    {
        "title": "Full Stack .Net Developer",
        "link": "https://jobs.bdjobs.com/jobdetails/?id=1435673&fcatId=8&ln=1",
        "deadline": "Deadline:20 Dec2025"
    },
    {
        "title": "Assistant Manager- Full Stack Developer",
        "link": "https://jobs.bdjobs.com/jobdetails/?id=1435525&fcatId=8&ln=1",
        "deadline": "Deadline:31 Dec2025"
    },
    {
        "title": "Lecturer",
        "link": "https://jobs.bdjobs.com/jobdetails/?id=1435465&fcatId=8&ln=1",
        "deadline": "Deadline:14 Dec2025"
    },
    {
        "title": "QA Engineer - Software",
        "link": "https://jobs.bdjobs.com/jobdetails/?id=1435376&fcatId=8&ln=1",
        "deadline": "Deadline:31 Dec2025"
    },
    {
        "title": "WordPress QA Engineer Intern",
        "link": "https://jobs.bdjobs.com/jobdetails/?id=1435294&fcatId=8&ln=1",
        "deadline": "Deadline:16 Dec2025"
    },
    {
        "title": "Intern- Technical Support",
        "link": "https://jobs.bdjobs.com/jobdetails/?id=1435319&fcatId=8&ln=1",
        "deadline": "Deadline:15 Dec2025"
    },
    {
        "title": "Webflow Developer - Internship (Web Design Khulna)",
        "link": "https://jobs.bdjobs.com/jobdetails/?id=1435297&fcatId=8&ln=1",
        "deadline": "Deadline:16 Dec2025"
    },
    {
        "title": "Executive - IT (Manpower Export Company)",
        "link": "https://jobs.bdjobs.com/jobdetails/?id=1434921&fcatId=8&ln=1",
        "deadline": "Deadline:31 Dec2025"
    },
    {
        "title": "Unit Head (Artificial Intelligence- Digital Banking)",
        "link": "https://jobs.bdjobs.com/jobdetails/?id=1435081&fcatId=8&ln=1",
        "deadline": "Deadline:10 Dec2025"
    },
    {
        "title": "SEO Specialist",
        "link": "https://jobs.bdjobs.com/jobdetails/?id=1435072&fcatId=8&ln=1",
        "deadline": "Deadline:10 Dec2025"
    },
    {
        "title": "Officer/Senior Officer- IT",
        "link": "https://jobs.bdjobs.com/jobdetails/?id=1434815&fcatId=8&ln=1",
        "deadline": "Deadline:20 Dec2025"
    },
    {
        "title": "Webflow Developer - Internship (Web Design Khulna)",
        "link": "https://jobs.bdjobs.com/jobdetails/?id=1434893&fcatId=8&ln=1",
        "deadline": "Deadline:10 Dec2025"
    },
    {
        "title": "Software Architect/ AGM - Software Development",
        "link": "https://jobs.bdjobs.com/jobdetails/?id=1434873&fcatId=8&ln=1",
        "deadline": "Deadline:30 Dec2025"
    },
    {
        "title": "Business Intelligence (BI) Analyst",
        "link": "https://jobs.bdjobs.com/jobdetails/?id=1434846&fcatId=8&ln=1",
        "deadline": "Deadline:30 Dec2025"
    },
    {
        "title": "UI/UX Designer (Cybersecurity SaaS)",
        "link": "https://jobs.bdjobs.com/jobdetails/?id=1434793&fcatId=8&ln=1",
        "deadline": "Deadline:30 Dec2025"
    },
    {
        "title": "UI/UX Designer (Sr. Executive)",
        "link": "https://jobs.bdjobs.com/jobdetails/?id=1434768&fcatId=8&ln=1",
        "deadline": "Deadline:30 Dec2025"
    },
    {
        "title": "Intern",
        "link": "https://jobs.bdjobs.com/jobdetails/?id=1434755&fcatId=8&ln=1",
        "deadline": "Deadline:15 Dec2025"
    },
    {
        "title": "Technical Support Intern",
        "link": "https://jobs.bdjobs.com/jobdetails/?id=1434745&fcatId=8&ln=1",
        "deadline": "Deadline:10 Dec2025"
    },
    {
        "title": "Senior Software Developer (.NET / C# )",
        "link": "https://jobs.bdjobs.com/jobdetails/?id=1434101&fcatId=8&ln=1",
        "deadline": "Deadline:29 Dec2025"
    },
    {
        "title": "Sr. Executive MIS (Dyeing Automation)",
        "link": "https://jobs.bdjobs.com/jobdetails/?id=1434680&fcatId=8&ln=1",
        "deadline": "Deadline:30 Dec2025"
    },
    {
        "title": "Junior Executive, Data Entry - ERP/MIS",
        "link": "https://jobs.bdjobs.com/jobdetails/?id=1434679&fcatId=8&ln=1",
        "deadline": "Deadline:30 Dec2025"
    },
    {
        "title": "Executive / Sr. Executive",
        "link": "https://jobs.bdjobs.com/jobdetails/?id=1433597&fcatId=8&ln=1",
        "deadline": "Deadline:9 Dec2025"
    },
    {
        "title": "Full Time Web Developer Laravel",
        "link": "https://jobs.bdjobs.com/jobdetails/?id=1430737&fcatId=8&ln=1",
        "deadline": "Deadline:15 Dec2025"
    },
    {
        "title": "Full Time Web Developer Dot Net",
        "link": "https://jobs.bdjobs.com/jobdetails/?id=1430736&fcatId=8&ln=1",
        "deadline": "Deadline:15 Dec2025"
    },
    {
        "title": "System & Business Quality Control (QC) Executive/Sr. Executive",
        "link": "https://jobs.bdjobs.com/jobdetails/?id=1434447&fcatId=8&ln=1",
        "deadline": "Deadline:25 Dec2025"
    },
    {
        "title": "Senior Executive (Software Sales)",
        "link": "https://jobs.bdjobs.com/jobdetails/?id=1434484&fcatId=8&ln=1",
        "deadline": "Deadline:9 Dec2025"
    },
    {
        "title": "Web Developer - English Carnival Bangladesh",
        "link": "https://jobs.bdjobs.com/jobdetails/?id=1433948&fcatId=8&ln=1",
        "deadline": "Deadline:7 Dec2025"
    },
    {
        "title": "Lead, Software Engineering & DevOps",
        "link": "https://jobs.bdjobs.com/jobdetails/?id=1434020&fcatId=8&ln=1",
        "deadline": "Deadline:7 Dec2025"
    },
    {
        "title": "Digital Marketing Specialist",
        "link": "https://jobs.bdjobs.com/jobdetails/?id=1434355&fcatId=8&ln=1",
        "deadline": "Deadline:5 Dec2025"
    },
    {
        "title": "Executive-Material Development & Training",
        "link": "https://jobs.bdjobs.com/jobdetails/?id=1434385&fcatId=8&ln=1",
        "deadline": "Deadline:29 Dec2025"
    },
    {
        "title": "Frontend Engineer (Gutenberg Specialist)",
        "link": "https://jobs.bdjobs.com/jobdetails/?id=1434328&fcatId=8&ln=1",
        "deadline": "Deadline:28 Dec2025"
    },
    {
        "title": "Sr. Executive - IT ( Hardware, Software & Networking)",
        "link": "https://jobs.bdjobs.com/jobdetails/?id=1434196&fcatId=8&ln=1",
        "deadline": "Deadline:27 Dec2025"
    },
    {
        "title": "Software / Sr. Software Engineer",
        "link": "https://jobs.bdjobs.com/jobdetails/?id=1434167&fcatId=8&ln=1",
        "deadline": "Deadline:25 Dec2025"
    },
    {
        "title": "Officer - Documentation and Analysis (Software Development)",
        "link": "https://jobs.bdjobs.com/jobdetails/?id=1427270&fcatId=8&ln=1",
        "deadline": "Deadline:26 Dec2025"
    },
    {
        "title": "Software Quality Assurance Engineer",
        "link": "https://jobs.bdjobs.com/jobdetails/?id=1433990&fcatId=8&ln=1",
        "deadline": "Deadline:27 Dec2025"
    },
    {
        "title": "Software Engineer",
        "link": "https://jobs.bdjobs.com/jobdetails/?id=1433159&fcatId=8&ln=1",
        "deadline": "Deadline:25 Dec2025"
    },
    {
        "title": "Training & Operation (Intern)",
        "link": "https://jobs.bdjobs.com/jobdetails/?id=1433814&fcatId=8&ln=1",
        "deadline": "Deadline:11 Dec2025"
    },
    {
        "title": "Head of Digital Transformation",
        "link": "https://jobs.bdjobs.com/jobdetails/?id=1434002&fcatId=8&ln=1",
        "deadline": "Deadline:27 Dec2025"
    },
    {
        "title": "Sr. QA Engineer",
        "link": "https://jobs.bdjobs.com/jobdetails/?id=1433745&fcatId=8&ln=1",
        "deadline": "Deadline:26 Dec2025"
    },
    {
        "title": "Country Head",
        "link": "https://jobs.bdjobs.com/jobdetails/?id=1433819&fcatId=8&ln=1",
        "deadline": "Deadline:17 Dec2025"
    },
    {
        "title": "Technician - CSE",
        "link": "https://jobs.bdjobs.com/jobdetails/?id=1433884&fcatId=8&ln=1",
        "deadline": "Deadline:7 Dec2025"
    },
    {
        "title": "WordPress Project Manager (Remote)",
        "link": "https://jobs.bdjobs.com/jobdetails/?id=1433296&fcatId=8&ln=1",
        "deadline": "Deadline:10 Dec2025"
    },
    {
        "title": "Junior Software (Python) Developer",
        "link": "https://jobs.bdjobs.com/jobdetails/?id=1433030&fcatId=8&ln=1",
        "deadline": "Deadline:24 Dec2025"
    },
    {
        "title": "Senior DevOps Engineer (AWS & Kubernetes)",
        "link": "https://jobs.bdjobs.com/jobdetails/?id=1433806&fcatId=8&ln=1",
        "deadline": "Deadline:6 Dec2025"
    },
    {
        "title": "Senior IT Executive",
        "link": "https://jobs.bdjobs.com/jobdetails/?id=1433773&fcatId=8&ln=1",
        "deadline": "Deadline:24 Dec2025"
    },
    {
        "title": "JavaScript Web Developer (1-4 Years Experience)",
        "link": "https://jobs.bdjobs.com/jobdetails/?id=1433608&fcatId=8&ln=1",
        "deadline": "Deadline:26 Dec2025"
    },
    {
        "title": "Intern - Backend Developer (Paid)",
        "link": "https://jobs.bdjobs.com/jobdetails/?id=1433657&fcatId=8&ln=1",
        "deadline": "Deadline:11 Dec2025"
    },
    {
        "title": "3D Designer/Visualizer Internship (Paid)",
        "link": "https://jobs.bdjobs.com/jobdetails/?id=1433638&fcatId=8&ln=1",
        "deadline": "Deadline:11 Dec2025"
    },
    {
        "title": "Paid Internship (Unity Game Developer)",
        "link": "https://jobs.bdjobs.com/jobdetails/?id=1433633&fcatId=8&ln=1",
        "deadline": "Deadline:11 Dec2025"
    },
    {
        "title": "WordPress Plugin Developer",
        "link": "https://jobs.bdjobs.com/jobdetails/?id=1433385&fcatId=8&ln=1",
        "deadline": "Deadline:25 Dec2025"
    },
    {
        "title": "Coordinator - Sales & Data Processing",
        "link": "https://jobs.bdjobs.com/jobdetails/?id=1433646&fcatId=8&ln=1",
        "deadline": "Deadline:6 Dec2025"
    },
    {
        "title": "Officer - IT",
        "link": "https://jobs.bdjobs.com/jobdetails/?id=1433357&fcatId=8&ln=1",
        "deadline": "Deadline:6 Dec2025"
    },
    {
        "title": "Digital Marketing & Video Editing Intern",
        "link": "https://jobs.bdjobs.com/jobdetails/?id=1433141&fcatId=8&ln=1",
        "deadline": "Deadline:10 Dec2025"
    },
    {
        "title": "NestJs Developer",
        "link": "https://jobs.bdjobs.com/jobdetails/?id=1433386&fcatId=8&ln=1",
        "deadline": "Deadline:5 Dec2025"
    },
    {
        "title": "Telesales Executive",
        "link": "https://jobs.bdjobs.com/jobdetails/?id=1433373&fcatId=8&ln=1",
        "deadline": "Deadline:24 Dec2025"
    },
    {
        "title": "IT Support with Digital Marketing Specialist",
        "link": "https://jobs.bdjobs.com/jobdetails/?id=1433376&fcatId=8&ln=1",
        "deadline": "Deadline:15 Dec2025"
    },
    {
        "title": "e-Government Procurement (e-GP) Tender Executive",
        "link": "https://jobs.bdjobs.com/jobdetails/?id=1433310&fcatId=8&ln=1",
        "deadline": "Deadline:25 Dec2025"
    },
    {
        "title": "IT Officer",
        "link": "https://jobs.bdjobs.com/jobdetails/?id=1433312&fcatId=8&ln=1",
        "deadline": "Deadline:25 Dec2025"
    },
    {
        "title": "Asst. Engineer/ Asst. Manager (IT Department)",
        "link": "https://jobs.bdjobs.com/jobdetails/?id=1433129&fcatId=8&ln=1",
        "deadline": "Deadline:25 Dec2025"
    },
    {
        "title": "Junior Software Engineer (Full Stack .Net & Angular)",
        "link": "https://jobs.bdjobs.com/jobdetails/?id=1433277&fcatId=8&ln=1",
        "deadline": "Deadline:25 Dec2025"
    },
    {
        "title": "Training & Operation (Intern)",
        "link": "https://jobs.bdjobs.com/jobdetails/?id=1433137&fcatId=8&ln=1",
        "deadline": "Deadline:10 Dec2025"
    },
    {
        "title": "Executive/Sr. Executive - ICT (Software Support)",
        "link": "https://jobs.bdjobs.com/jobdetails/?id=1433280&fcatId=8&ln=1",
        "deadline": "Deadline:5 Dec2025"
    },
    {
        "title": "Jr. Engineer / Engineer - Customer support & Helpdesk",
        "link": "https://jobs.bdjobs.com/jobdetails/?id=1433249&fcatId=8&ln=1",
        "deadline": "Deadline:25 Dec2025"
    },
    {
        "title": "Head of Operations (Future COO)",
        "link": "https://jobs.bdjobs.com/jobdetails/?id=1433217&fcatId=8&ln=1",
        "deadline": "Deadline:25 Dec2025"
    },
    {
        "title": "Lead Developer",
        "link": "https://jobs.bdjobs.com/jobdetails/?id=1433147&fcatId=8&ln=1",
        "deadline": "Deadline:12 Dec2025"
    },
    {
        "title": "Associate Software Quality Assurance Engineer",
        "link": "https://jobs.bdjobs.com/jobdetails/?id=1433227&fcatId=8&ln=1",
        "deadline": "Deadline:25 Dec2025"
    },
    {
        "title": "Software Project Coordinator",
        "link": "https://jobs.bdjobs.com/jobdetails/?id=1433097&fcatId=8&ln=1",
        "deadline": "Deadline:25 Dec2025"
    },
    {
        "title": "C++ Developer",
        "link": "https://jobs.bdjobs.com/jobdetails/?id=1433201&fcatId=8&ln=1",
        "deadline": "Deadline:25 Dec2025"
    },
    {
        "title": "Software Developer (ASP.NET/CORE)",
        "link": "https://jobs.bdjobs.com/jobdetails/?id=1433193&fcatId=8&ln=1",
        "deadline": "Deadline:25 Dec2025"
    },
    {
        "title": "Intern Software Developer",
        "link": "https://jobs.bdjobs.com/jobdetails/?id=1433010&fcatId=8&ln=1",
        "deadline": "Deadline:9 Dec2025"
    },
    {
        "title": "Assistant Sales Manager",
        "link": "https://jobs.bdjobs.com/jobdetails/?id=1432802&fcatId=8&ln=1",
        "deadline": "Deadline:24 Dec2025"
    },
    {
        "title": "E-commerce & Digital Marketing Specialist",
        "link": "https://jobs.bdjobs.com/jobdetails/?id=1432745&fcatId=8&ln=1",
        "deadline": "Deadline:24 Dec2025"
    },
    {
        "title": "Business Development Officer - Linexis IT Institute",
        "link": "https://jobs.bdjobs.com/jobdetails/?id=1432513&fcatId=8&ln=1",
        "deadline": "Deadline:23 Dec2025"
    },
    {
        "title": "Software Engineer",
        "link": "https://jobs.bdjobs.com/jobdetails/?id=1432752&fcatId=8&ln=1",
        "deadline": "Deadline:24 Dec2025"
    },
    {
        "title": "Senior SQA Engineer / Senior Software Test Engineer",
        "link": "https://jobs.bdjobs.com/jobdetails/?id=1432726&fcatId=8&ln=1",
        "deadline": "Deadline:6 Dec2025"
    },
    {
        "title": "DevOps Engineer - System Design & Scaling",
        "link": "https://jobs.bdjobs.com/jobdetails/?id=1432716&fcatId=8&ln=1",
        "deadline": "Deadline:6 Dec2025"
    },
    {
        "title": "Senior Business Analyst (BA)",
        "link": "https://jobs.bdjobs.com/jobdetails/?id=1432704&fcatId=8&ln=1",
        "deadline": "Deadline:6 Dec2025"
    },
    {
        "title": "AI Engineer",
        "link": "https://jobs.bdjobs.com/jobdetails/?id=1432611&fcatId=8&ln=1",
        "deadline": "Deadline:15 Dec2025"
    },
    {
        "title": "Sales Executive (Software & Hardware Solutions)",
        "link": "https://jobs.bdjobs.com/jobdetails/?id=1432447&fcatId=8&ln=1",
        "deadline": "Deadline:23 Dec2025"
    },
    {
        "title": "Computer Operator",
        "link": "https://jobs.bdjobs.com/jobdetails/?id=1432108&fcatId=8&ln=1",
        "deadline": "Deadline:22 Dec2025"
    },
    {
        "title": "Graphics & Motion Designer",
        "link": "https://jobs.bdjobs.com/jobdetails/?id=1432398&fcatId=8&ln=1",
        "deadline": "Deadline:22 Dec2025"
    },
    {
        "title": "Senior Software Test Engineer (Walton Mobile)",
        "link": "https://jobs.bdjobs.com/jobdetails/?id=1432212&fcatId=8&ln=1",
        "deadline": "Deadline:22 Dec2025"
    },
    {
        "title": "Programmer - Intern",
        "link": "https://jobs.bdjobs.com/jobdetails/?id=1432155&fcatId=8&ln=1",
        "deadline": "Deadline:7 Dec2025"
    },
    {
        "title": "Executive - IT Department",
        "link": "https://jobs.bdjobs.com/jobdetails/?id=1432057&fcatId=8&ln=1",
        "deadline": "Deadline:22 Dec2025"
    },
    {
        "title": "Android Developer",
        "link": "https://jobs.bdjobs.com/jobdetails/?id=1431954&fcatId=8&ln=1",
        "deadline": "Deadline:20 Dec2025"
    },
    {
        "title": "Mobile App Developer (Kotlin)",
        "link": "https://jobs.bdjobs.com/jobdetails/?id=1431926&fcatId=8&ln=1",
        "deadline": "Deadline:20 Dec2025"
    },
    {
        "title": "Product Manager, Mobile Apps",
        "link": "https://jobs.bdjobs.com/jobdetails/?id=1431622&fcatId=8&ln=1",
        "deadline": "Deadline:6 Dec2025"
    },
    {
        "title": "Software Engineer (.NET Core & Angular)",
        "link": "https://jobs.bdjobs.com/jobdetails/?id=1431583&fcatId=8&ln=1",
        "deadline": "Deadline:14 Dec2025"
    },
    {
        "title": "Frontend Developer (React) - with Backend & Python Exposure",
        "link": "https://jobs.bdjobs.com/jobdetails/?id=1431433&fcatId=8&ln=1",
        "deadline": "Deadline:20 Dec2025"
    },
    {
        "title": "Graphic Design Specialist",
        "link": "https://jobs.bdjobs.com/jobdetails/?id=1431172&fcatId=8&ln=1",
        "deadline": "Deadline:19 Dec2025"
    },
    {
        "title": "Executive Business Development",
        "link": "https://jobs.bdjobs.com/jobdetails/?id=1431208&fcatId=8&ln=1",
        "deadline": "Deadline:19 Dec2025"
    },
    {
        "title": "App Development Engineer",
        "link": "https://jobs.bdjobs.com/jobdetails/?id=1431146&fcatId=8&ln=1",
        "deadline": "Deadline:19 Dec2025"
    },
    {
        "title": "Network and System Engineer",
        "link": "https://jobs.bdjobs.com/jobdetails/?id=1431048&fcatId=8&ln=1",
        "deadline": "Deadline:19 Dec2025"
    },
    {
        "title": "Video Editor & Motion Designer",
        "link": "https://jobs.bdjobs.com/jobdetails/?id=1431054&fcatId=8&ln=1",
        "deadline": "Deadline:19 Dec2025"
    },
    {
        "title": "Content Writer (English)",
        "link": "https://jobs.bdjobs.com/jobdetails/?id=1431023&fcatId=8&ln=1",
        "deadline": "Deadline:19 Dec2025"
    },
    {
        "title": "Intern - IT",
        "link": "https://jobs.bdjobs.com/jobdetails/?id=1431029&fcatId=8&ln=1",
        "deadline": "Deadline:19 Dec2025"
    },
    {
        "title": "Network Engineer",
        "link": "https://jobs.bdjobs.com/jobdetails/?id=1429884&fcatId=8&ln=1",
        "deadline": "Deadline:15 Dec2025"
    },
    {
        "title": "App Developer (Laravel)",
        "link": "https://jobs.bdjobs.com/jobdetails/?id=1430811&fcatId=8&ln=1",
        "deadline": "Deadline:18 Dec2025"
    },
    {
        "title": "Sr. Executive (ERP Implementation)",
        "link": "https://jobs.bdjobs.com/jobdetails/?id=1430800&fcatId=8&ln=1",
        "deadline": "Deadline:18 Dec2025"
    },
    {
        "title": "Full Stack Web Developer",
        "link": "https://jobs.bdjobs.com/jobdetails/?id=1430693&fcatId=8&ln=1",
        "deadline": "Deadline:17 Dec2025"
    },
    {
        "title": "Full-Stack Digital Marketer (Beauty Industry)",
        "link": "https://jobs.bdjobs.com/jobdetails/?id=1430750&fcatId=8&ln=1",
        "deadline": "Deadline:18 Dec2025"
    },
    {
        "title": "Computer Programmer / Software Engineer",
        "link": "https://jobs.bdjobs.com/jobdetails/?id=1430684&fcatId=8&ln=1",
        "deadline": "Deadline:18 Dec2025"
    },
    {
        "title": "IT & Digital Marketing Executive",
        "link": "https://jobs.bdjobs.com/jobdetails/?id=1430574&fcatId=8&ln=1",
        "deadline": "Deadline:10 Dec2025"
    },
    {
        "title": "Product Manager - PA, Conference Systems & Solutions",
        "link": "https://jobs.bdjobs.com/jobdetails/?id=1430509&fcatId=8&ln=1",
        "deadline": "Deadline:18 Dec2025"
    },
    {
        "title": "Business Analyst Specialist",
        "link": "https://jobs.bdjobs.com/jobdetails/?id=1430359&fcatId=8&ln=1",
        "deadline": "Deadline:17 Dec2025"
    },
    {
        "title": "Executive/ Sr. Executive, IT",
        "link": "https://jobs.bdjobs.com/jobdetails/?id=1430220&fcatId=8&ln=1",
        "deadline": "Deadline:17 Dec2025"
    },
    {
        "title": "App Developer (React Native)",
        "link": "https://jobs.bdjobs.com/jobdetails/?id=1429782&fcatId=8&ln=1",
        "deadline": "Deadline:16 Dec2025"
    },
    {
        "title": "Assistant Manager (IT Training Division)- Sales & Marketing",
        "link": "https://jobs.bdjobs.com/jobdetails/?id=1430149&fcatId=8&ln=1",
        "deadline": "Deadline:17 Dec2025"
    },
    {
        "title": "Senior Executive/Assistant Manager (Linux System Admin)",
        "link": "https://jobs.bdjobs.com/jobdetails/?id=1429686&fcatId=8&ln=1",
        "deadline": "Deadline:16 Dec2025"
    },
    {
        "title": "SEO Specialist",
        "link": "https://jobs.bdjobs.com/jobdetails/?id=1430148&fcatId=8&ln=1",
        "deadline": "Deadline:17 Dec2025"
    },
    {
        "title": "Technical Content & RFP Specialist",
        "link": "https://jobs.bdjobs.com/jobdetails/?id=1429678&fcatId=8&ln=1",
        "deadline": "Deadline:16 Dec2025"
    },
    {
        "title": "Assistant Manager",
        "link": "https://jobs.bdjobs.com/jobdetails/?id=1429890&fcatId=8&ln=1",
        "deadline": "Deadline:16 Dec2025"
    },
    {
        "title": "Software Engineer (Full Stack)",
        "link": "https://jobs.bdjobs.com/jobdetails/?id=1429788&fcatId=8&ln=1",
        "deadline": "Deadline:16 Dec2025"
    },
    {
        "title": "IT - Developer",
        "link": "https://jobs.bdjobs.com/jobdetails/?id=1429718&fcatId=8&ln=1",
        "deadline": "Deadline:16 Dec2025"
    },
    {
        "title": "Network Engineer - ISP",
        "link": "https://jobs.bdjobs.com/jobdetails/?id=1429524&fcatId=8&ln=1",
        "deadline": "Deadline:15 Dec2025"
    },
    {
        "title": "Java Developer (Spring Boot, React, JasperReports)",
        "link": "https://jobs.bdjobs.com/jobdetails/?id=1429397&fcatId=8&ln=1",
        "deadline": "Deadline:15 Dec2025"
    },
    {
        "title": "WordPress Developer",
        "link": "https://jobs.bdjobs.com/jobdetails/?id=1428882&fcatId=8&ln=1",
        "deadline": "Deadline:13 Dec2025"
    },
    {
        "title": "Junior WordPress Developer",
        "link": "https://jobs.bdjobs.com/jobdetails/?id=1429255&fcatId=8&ln=1",
        "deadline": "Deadline:13 Dec2025"
    },
    {
        "title": "MIS Officer",
        "link": "https://jobs.bdjobs.com/jobdetails/?id=1429124&fcatId=8&ln=1",
        "deadline": "Deadline:13 Dec2025"
    },
    {
        "title": "IT Executives (Senior / Junior)",
        "link": "https://jobs.bdjobs.com/jobdetails/?id=1429158&fcatId=8&ln=1",
        "deadline": "Deadline:13 Dec2025"
    },
    {
        "title": "Junior Web Developer",
        "link": "https://jobs.bdjobs.com/jobdetails/?id=1429106&fcatId=8&ln=1",
        "deadline": "Deadline:13 Dec2025"
    },
    {
        "title": "Technical Manager",
        "link": "https://jobs.bdjobs.com/jobdetails/?id=1429035&fcatId=8&ln=1",
        "deadline": "Deadline:13 Dec2025"
    },
    {
        "title": "Software Engineer (.Net Core / Blazor - Web Developer)",
        "link": "https://jobs.bdjobs.com/jobdetails/?id=1428993&fcatId=8&ln=1",
        "deadline": "Deadline:13 Dec2025"
    },
    {
        "title": ".NET Developer",
        "link": "https://jobs.bdjobs.com/jobdetails/?id=1428996&fcatId=8&ln=1",
        "deadline": "Deadline:13 Dec2025"
    },
    {
        "title": "Manager - Programmer",
        "link": "https://jobs.bdjobs.com/jobdetails/?id=1428965&fcatId=8&ln=1",
        "deadline": "Deadline:12 Dec2025"
    },
    {
        "title": "Network Engineer",
        "link": "https://jobs.bdjobs.com/jobdetails/?id=1428901&fcatId=8&ln=1",
        "deadline": "Deadline:13 Dec2025"
    },
    {
        "title": "App Developer (Bubble Webflow No Code )",
        "link": "https://jobs.bdjobs.com/jobdetails/?id=1428885&fcatId=8&ln=1",
        "deadline": "Deadline:12 Dec2025"
    },
    {
        "title": "Head of IT",
        "link": "https://jobs.bdjobs.com/jobdetails/?id=1428865&fcatId=8&ln=1",
        "deadline": "Deadline:12 Dec2025"
    },
    {
        "title": "Web Developer",
        "link": "https://jobs.bdjobs.com/jobdetails/?id=1428859&fcatId=8&ln=1",
        "deadline": "Deadline:12 Dec2025"
    },
    {
        "title": "Senior Support Executive - ERP",
        "link": "https://jobs.bdjobs.com/jobdetails/?id=1428664&fcatId=8&ln=1",
        "deadline": "Deadline:12 Dec2025"
    },
    {
        "title": "Executive, IT & E-Commerce",
        "link": "https://jobs.bdjobs.com/jobdetails/?id=1428568&fcatId=8&ln=1",
        "deadline": "Deadline:12 Dec2025"
    },
    {
        "title": "Officer - IT & Data Entry",
        "link": "https://jobs.bdjobs.com/jobdetails/?id=1428631&fcatId=8&ln=1",
        "deadline": "Deadline:12 Dec2025"
    },
    {
        "title": "Assistant Project Manager",
        "link": "https://jobs.bdjobs.com/jobdetails/?id=1428468&fcatId=8&ln=1",
        "deadline": "Deadline:12 Dec2025"
    },
    {
        "title": "Digital Transformation Officer",
        "link": "https://jobs.bdjobs.com/jobdetails/?id=1428464&fcatId=8&ln=1",
        "deadline": "Deadline:11 Dec2025"
    },
    {
        "title": "Executive/Sr. Executive (Software Development)",
        "link": "https://jobs.bdjobs.com/jobdetails/?id=1428401&fcatId=8&ln=1",
        "deadline": "Deadline:11 Dec2025"
    },
    {
        "title": "Jr. Officer (ERP - Production)",
        "link": "https://jobs.bdjobs.com/jobdetails/?id=1427725&fcatId=8&ln=1",
        "deadline": "Deadline:10 Dec2025"
    },
    {
        "title": "Software Engineer",
        "link": "https://jobs.bdjobs.com/jobdetails/?id=1427921&fcatId=8&ln=1",
        "deadline": "Deadline:10 Dec2025"
    },
    {
        "title": "Website Developer",
        "link": "https://jobs.bdjobs.com/jobdetails/?id=1427729&fcatId=8&ln=1",
        "deadline": "Deadline:10 Dec2025"
    },
    {
        "title": "Server, Hardware & Network Administrator",
        "link": "https://jobs.bdjobs.com/jobdetails/?id=1427718&fcatId=8&ln=1",
        "deadline": "Deadline:10 Dec2025"
    },
    {
        "title": "Andriod Application Developer",
        "link": "https://jobs.bdjobs.com/jobdetails/?id=1427684&fcatId=8&ln=1",
        "deadline": "Deadline:10 Dec2025"
    },
    {
        "title": "Senior Manager/ Manager - Presales",
        "link": "https://jobs.bdjobs.com/jobdetails/?id=1427560&fcatId=8&ln=1",
        "deadline": "Deadline:9 Dec2025"
    },
    {
        "title": "Software Engineer (Microsoft DOT.NET Platform)",
        "link": "https://jobs.bdjobs.com/jobdetails/?id=1427496&fcatId=8&ln=1",
        "deadline": "Deadline:9 Dec2025"
    },
    {
        "title": "Senior Java Developer",
        "link": "https://jobs.bdjobs.com/jobdetails/?id=1427411&fcatId=8&ln=1",
        "deadline": "Deadline:9 Dec2025"
    },
    {
        "title": "Data Analyst",
        "link": "https://jobs.bdjobs.com/jobdetails/?id=1427273&fcatId=8&ln=1",
        "deadline": "Deadline:9 Dec2025"
    },
    {
        "title": "MTO (ERP)",
        "link": "https://jobs.bdjobs.com/jobdetails/?id=1427274&fcatId=8&ln=1",
        "deadline": "Deadline:8 Dec2025"
    },
    {
        "title": "Sr. Software Engineer (ASP.NET, KendoUI)",
        "link": "https://jobs.bdjobs.com/jobdetails/?id=1427034&fcatId=8&ln=1",
        "deadline": "Deadline:8 Dec2025"
    },
    {
        "title": "Project Manager - Python / Django Specialist",
        "link": "https://jobs.bdjobs.com/jobdetails/?id=1426915&fcatId=8&ln=1",
        "deadline": "Deadline:8 Dec2025"
    },
    {
        "title": "Assistant Vice President, IT",
        "link": "https://jobs.bdjobs.com/jobdetails/?id=1426000&fcatId=8&ln=1",
        "deadline": "Deadline:5 Dec2025"
    },
    {
        "title": "Software Engineer (Laravel, PHP & Tall Stack) - Dhaka Office Based",
        "link": "https://jobs.bdjobs.com/jobdetails/?id=1426321&fcatId=8&ln=1",
        "deadline": "Deadline:5 Dec2025"
    },
    {
        "title": "Graphic Designer",
        "link": "https://jobs.bdjobs.com/jobdetails/?id=1426192&fcatId=8&ln=1",
        "deadline": "Deadline:5 Dec2025"
    },
    {
        "title": "UI/UX Designer",
        "link": "https://jobs.bdjobs.com/jobdetails/?id=1426067&fcatId=8&ln=1",
        "deadline": "Deadline:5 Dec2025"
    },
    {
        "title": "Senior Go Developer (Security & Compliance Engineering)",
        "link": "https://jobs.bdjobs.com/jobdetails/?id=1425899&fcatId=8&ln=1",
        "deadline": "Deadline:5 Dec2025"
    }
]